[
    {"name": "Jane Street", "type": "Trading Firm"},
    {"name": "Citadel", "type": "Hedge Fund"},
    {"name": "Two Sigma", "type": "Hedge Fund"},
    {"name": "DE Shaw", "type": "Hedge Fund"},
    {"name": "Jump Trading", "type": "Trading Firm"},
    {"name": "HRT", "type": "Trading Firm"},
    {"name": "Optiver", "type": "Trading Firm"},
    {"name": "Renaissance Technologies", "type": "Hedge Fund"},
    {"name": "AQR", "type": "Hedge Fund"},
    {"name": "Millennium", "type": "Hedge Fund"},
    {"name": "Point72", "type": "Hedge Fund"},
    {"name": "Bridgewater", "type": "Hedge Fund"},
    {"name": "Virtu Financial", "type": "Trading Firm"},
    {"name": "Tower Research", "type": "Trading Firm"},
    {"name": "IMC Trading", "type": "Trading Firm"},

    {"name": "DRW", "type": "Trading Firm"},
    {"name": "TRC", "type": "Trading Firm"},
    {"name": "Headlands Technologies", "type": "Trading Firm"},
    {"name": "WorldQuant", "type": "Hedge Fund"},
    {"name": "Schonfeld Strategic Advisors", "type": "Hedge Fund"},
    {"name": "GSA", "type": "Hedge Fund"},
    {"name": "Verition Fund Management", "type": "Hedge Fund"},
    {"name": "Susquehanna International Group", "type": "Trading Firm"},
    {"name": "Akuna Capital", "type": "Trading Firm"},
    {"name": "XTX Markets", "type": "Trading Firm"},
    {"name": "Flow Traders", "type": "Trading Firm"},
    {"name": "Belvedere Trading", "type": "Trading Firm"},
    {"name": "G-Research", "type": "Hedge Fund"},
    {"name": "Squarepoint", "type": "Hedge Fund"},
    {"name": "Tibra Capital", "type": "Trading Firm"},
    {"name": "Da Vinci", "type": "Hedge Fund"},
    {"name": "Wolverine Trading", "type": "Trading Firm"},
    {"name": "3Red Partners", "type": "Hedge Fund"},
    {"name": "Geneva Trading", "type": "Trading Firm"},
    {"name": "OMC", "type": "Trading Firm"},
    {"name": "TIC", "type": "Trading Firm"},
    {"name": "Maven Securities", "type": "Trading Firm"},
    {"name": "Quantlab Financial", "type": "Trading Firm"},
    {"name": "TransMarket Group", "type": "Trading Firm"},
    {"name": "XR Trading", "type": "Trading Firm"},
    {"name": "FNY Capital", "type": "Trading Firm"},
    {"name": "DV Trading", "type": "Trading Firm"},
    {"name": "Radix Trading", "type": "Trading Firm"},
    {"name": "OpenQuant", "type": "Trading Firm"},
    
    {"name": "Winton", "type": "Hedge Fund"},
    {"name": "Arrowstreet Capital", "type": "Hedge Fund"},

    {"name": "Goldman Sachs", "type": "Global Bank"},
    {"name": "Morgan Stanley", "type": "Global Bank"},
    {"name": "JPMorgan Chase", "type": "Global Bank"},
    {"name": "Bank of America", "type": "Global Bank"},
    {"name": "Citi", "type": "Global Bank"},

    {"name": "Goldman Sachs ", "type": "Global Bank"},
    {"name": "Morgan Stanley ", "type": "Global Bank"},
    {"name": "J.P. Morgan ", "type": "Global Bank"},
    {"name": "Barclays ", "type": "Global Bank"},
    {"name": "Citi ", "type": "Global Bank"},
    {"name": "HSBC ", "type": "Global Bank"},
    {"name": "Graviton Research Capital", "type": "Trading Firm"},
    {"name": "WorldQuant ", "type": "Hedge Fund"},
    {"name": "Tower Research Capital ", "type": "Trading Firm"},
    {"name": "AlphaGrep Securities", "type": "Trading Firm"},
    {"name": "Futures First", "type": "Trading Firm"},

    {"name": "Edelweiss Group", "type": "Asset Manager"},
    {"name": "IIFL Securities", "type": "Asset Manager"},
    {"name": "HDFC Asset Management", "type": "Asset Manager"},
    {"name": "ICICI Prudential AMC", "type": "Asset Manager"},
    {"name": "SBI Funds Management", "type": "Asset Manager"},
    {"name": "Aditya Birla Sun Life AMC", "type": "Asset Manager"},
    {"name": "Kotak Mahindra AMC", "type": "Asset Manager"},
    {"name": "Nippon India Mutual Fund", "type": "Asset Manager"},
    {"name": "UTI Asset Management", "type": "Asset Manager"},
    {"name": "State Bank of India", "type": "Bank"},
    {"name": "HDFC Bank", "type": "Bank"},
    {"name": "Axis Bank", "type": "Bank"},
    {"name": "Kotak Mahindra Bank", "type": "Bank"},
    {"name": "Zerodha", "type": "FinTech"},
    {"name": "Upstox", "type": "FinTech"},
    {"name": "Groww", "type": "FinTech"},
    {"name": "Angel One", "type": "FinTech"},
    {"name": "Quantsapp", "type": "FinTech"},

    {"name": "RMB - Rand Merchant Bank", "type": "Bank"},
    {"name": "Allan Gray", "type": "Asset Manager"},
    {"name": "Ninety One", "type": "Asset Manager"},
    {"name": "Coronation Fund Managers", "type": "Asset Manager"},
    {"name": "Futuregrowth Asset Management", "type": "Asset Manager"},
    {"name": "Sygnia", "type": "Asset Manager"},
    {"name": "Sanlam Investments", "type": "Asset Manager"},
    {"name": "Old Mutual", "type": "Asset Manager"},
    {"name": "PSG", "type": "Asset Manager"},
    {"name": "Absa Group", "type": "Bank"},
    {"name": "Standard Bank Group", "type": "Bank"},
    {"name": "Nedbank", "type": "Bank"},
    {"name": "Momentum", "type": "Asset Manager"},
    {"name": "Discovery Limited", "type": "Asset Manager"},
    {"name": "Capitec", "type": "Bank"},
    {"name": "PIC", "type": "Asset Manager"},
    {"name": "Taquanta Asset Managers", "type": "Asset Manager"},
    {"name": "Phoenix Group", "type": "Asset Manager"},
    {"name": "Obsidian", "type": "Asset Manager"},
    {"name": "Alexforbes", "type": "Asset Manager"},
    {"name": "African Bank", "type": "Bank"},
    {"name": "Investec", "type": "Bank"},
    {"name": "Sasfin", "type": "Bank"}
]
